schmelzen/__init__.py
schmelzen/common.py
schmelzen/schmelzen.py
schmelzen-0.0.2.dist-info/LICENSE
schmelzen-0.0.2.dist-info/METADATA
schmelzen-0.0.2.dist-info/WHEEL
schmelzen-0.0.2.dist-info/entry_points.txt
schmelzen-0.0.2.dist-info/top_level.txt
schmelzen-0.0.2.dist-info/RECORD
